{
  "matchedShows": [],
  "showsWithoutStats": [
    {
      "id": 2649,
      "key": "03ed7c95-eb19-4853-8c31-573af38202e2",
      "udi": "umb://document/03ed7c95eb1948538c31573af38202e2",
      "name": "Forsmag på Beslutningsmodellen.",
      "title": "Forsmag på Beslutningsmodellen."
    },
    {
      "id": 2694,
      "key": "fce713b4-7df0-46c7-9c7b-cfef1aabd09d",
      "udi": "umb://document/fce713b47df046c79c7bcfef1aabd09d",
      "name": "Hør mere om Søren.",
      "title": "Hør mere om Søren."
    }
  ],
  "statsMediaWithoutShow": []
}
