{
  "tab": "Layout",
  "name": "Britta Koch - Qigong",
  "tabsVisible": [
    "General",
    "Subscription",
    "Access & Price",
    "Layout",
    "Notifications",
    "SiteMap",
    "SEO",
    "Info"
  ],
  "skin": ["62"],
  "logoText": "Britta Koch - Qigong",
  "useLogoImage": "0",
  "logoImage": "",
  "useCoverImage": "1",
  "coverImage": {
    "focalPoint": {
      "left": 0.5,
      "top": 0.5
    },
    "src": "/media/2236/touann-gatouillat-vergos-nnmclx_eor4-unsplash.jpg",
    "crops": [
      {
        "alias": "Image",
        "width": 2000,
        "height": 600
      }
    ]
  },
  "coverImageMobile": "",
  "fadeCoverImage": "1",
  "textColor": ["67"],
  "coverTextPositionClass": "block",
  "headline": "",
  "description": "",
  "css": "",
  "javaScript": ""
}
