[
  {
    "id": 79153,
    "key": "70c0a3a3-90a3-4757-8651-05d1cc7a41b5",
    "udi": "umb://document/70c0a3a390a34757865105d1cc7a41b5",
    "name": "KBF-1392",
    "editUrl": "https://kiibee.dk/umbraco#/content/content/edit/79153",
    "contentTypeAlias": "payout",
    "published": true,
    "hasPublishedVersion": true,
    "createDate": "2023-03-17 12:12:27",
    "updateDate": "2023-03-17 12:48:29",
    "parentId": 78114,
    "path": "-1,1067,78110,78114,79153",
    "sortOrder": 1,
    "urls": ["/you-consulting/payouts/kbf-1392/"],
    "publicPayoutUrls": ["https://kiibee.dk/you-consulting/payouts/kbf-1392/"],
    "publicPayoutUrl": "https://kiibee.dk/you-consulting/payouts/kbf-1392/",
    "amount": "270",
    "amountNumber": 270,
    "isPaid": true,
    "payoutCreateDate": "2023-03-17 12:12:27",
    "candidateInvoiceProperties": [],
    "candidateInvoiceUrls": [],
    "directInvoiceUrls": [],
    "invoiceUdis": [],
    "invoiceEntities": [],
    "invoiceUrls": ["https://kiibee.dk/you-consulting/payouts/kbf-1392/"],
    "invoiceUrl": "https://kiibee.dk/you-consulting/payouts/kbf-1392/",
    "invoiceMatchStatus": "matched-public-payout-url",
    "properties": {
      "salesAmount": "1",
      "transactionFee": "5",
      "kiibeeCut": "15",
      "rentAmount": "0",
      "from": "2023-02-17 10:38:25",
      "rawEarnings": "300",
      "amount": "270",
      "isPaid": "1",
      "to": "2023-03-17 12:12:20",
      "transactionAmount": "15",
      "kiibeeCutAmount": "15"
    }
  },
  {
    "id": 78254,
    "key": "c2a44303-79ae-4372-8fb2-ea315f6d6f84",
    "udi": "umb://document/c2a4430379ae43728fb2ea315f6d6f84",
    "name": "KBF-1374",
    "editUrl": "https://kiibee.dk/umbraco#/content/content/edit/78254",
    "contentTypeAlias": "payout",
    "published": true,
    "hasPublishedVersion": true,
    "createDate": "2023-02-17 10:39:08",
    "updateDate": "2023-02-18 10:08:08",
    "parentId": 78114,
    "path": "-1,1067,78110,78114,78254",
    "sortOrder": 0,
    "urls": ["/you-consulting/payouts/kbf-1374/"],
    "publicPayoutUrls": ["https://kiibee.dk/you-consulting/payouts/kbf-1374/"],
    "publicPayoutUrl": "https://kiibee.dk/you-consulting/payouts/kbf-1374/",
    "amount": "270",
    "amountNumber": 270,
    "isPaid": true,
    "payoutCreateDate": "2023-02-17 10:39:08",
    "candidateInvoiceProperties": [],
    "candidateInvoiceUrls": [],
    "directInvoiceUrls": [],
    "invoiceUdis": [],
    "invoiceEntities": [],
    "invoiceUrls": ["https://kiibee.dk/you-consulting/payouts/kbf-1374/"],
    "invoiceUrl": "https://kiibee.dk/you-consulting/payouts/kbf-1374/",
    "invoiceMatchStatus": "matched-public-payout-url",
    "properties": {
      "salesAmount": "1",
      "transactionFee": "5",
      "kiibeeCut": "15",
      "rentAmount": "0",
      "from": "2023-02-13 20:28:41",
      "rawEarnings": "300",
      "amount": "270",
      "isPaid": "1",
      "to": "2023-02-17 10:38:25",
      "transactionAmount": "15",
      "kiibeeCutAmount": "15"
    }
  }
]
