[
  {
    "id": 55018,
    "key": "37f2c127-cd73-4cbb-bab8-bf020fd5a856",
    "udi": "umb://document/37f2c127cd734cbbbab8bf020fd5a856",
    "name": "63nj17122021195320",
    "contentTypeAlias": "purchase",
    "published": true,
    "hasPublishedVersion": true,
    "createDate": "2021-12-17 19:54:54",
    "updateDate": "2021-12-17 19:54:54",
    "parentId": 25345,
    "path": "-1,1067,25340,25345,55018",
    "sortOrder": 12,
    "urls": ["/ilona-margibell/purchases/63nj17122021195320/"],
    "fullName": "Ilona Margibell",
    "email": "ilonamargibell@gmail.com",
    "isPurchase": true,
    "downloads": 0,
    "streams": 0,
    "price": "249",
    "expireDate": "2022-01-16 19:54:53",
    "message": "Tak for køb af gavekortet (forudbestillingen). Bogen tilsendes ved udgivelsen.",
    "orderCreateDate": "2021-12-17 19:54:54",
    "mediaRelationUdis": ["umb://document/eb39a5eee85b4590b2049e4b1d7c609f"],
    "downloadUdis": [],
    "streamUdis": [],
    "mediaUdis": ["umb://document/eb39a5eee85b4590b2049e4b1d7c609f"],
    "downloadMediaCount": 0,
    "streamMediaCount": 0,
    "mediaCount": 1,
    "media": [
      {
        "udi": "umb://document/eb39a5eee85b4590b2049e4b1d7c609f",
        "key": "eb39a5ee-e85b-4590-b204-9e4b1d7c609f",
        "resolved": true,
        "id": 25348,
        "name": "Gavekort",
        "title": "Gavekort",
        "urls": ["/ilona-margibell/gavekort-til-bog/gavekort/"],
        "contentTypeAlias": "media",
        "videoID": "",
        "videoStatus": "",
        "videoThumbnailURL": "",
        "videoDownloadURL": "",
        "rawFile": "/media/2729/gavekort.pdf",
        "webContentURL": "",
        "thumbnail": "/media/2736/gavekort.jpg",
        "purchasePrice": "249",
        "rentalPrice": ""
      }
    ],
    "downloadMedia": [],
    "streamMedia": [],
    "mediaNames": ["Gavekort"],
    "mediaUrls": ["/ilona-margibell/gavekort-til-bog/gavekort/"],
    "videoDownloadURLs": [],
    "downloadMediaNames": [],
    "downloadMediaUrls": [],
    "downloadVideoDownloadURLs": [],
    "streamMediaNames": [],
    "streamMediaUrls": [],
    "streamVideoDownloadURLs": [],
    "properties": {
      "videoID": "",
      "email": "ilonamargibell@gmail.com",
      "streams": "",
      "downloads": "",
      "isPurchase": "1",
      "expireDate": "2022-01-16 19:54:53",
      "price": "249",
      "fullName": "Ilona Margibell",
      "message": "Tak for køb af gavekortet (forudbestillingen). Bogen tilsendes ved udgivelsen.",
      "media": "umb://document/eb39a5eee85b4590b2049e4b1d7c609f"
    }
  },
  {
    "id": 29141,
    "key": "75a30b7e-d5bf-459a-9650-859e37d6d4ca",
    "udi": "umb://document/75a30b7ed5bf459a9650859e37d6d4ca",
    "name": "nwe917012021135606",
    "contentTypeAlias": "purchase",
    "published": true,
    "hasPublishedVersion": true,
    "createDate": "2021-01-17 13:59:11",
    "updateDate": "2021-01-17 13:59:11",
    "parentId": 25345,
    "path": "-1,1067,25340,25345,29141",
    "sortOrder": 11,
    "urls": ["/ilona-margibell/purchases/nwe917012021135606/"],
    "fullName": "Anne Mette Rønnow Torp",
    "email": "amrt@mail.dk",
    "isPurchase": true,
    "downloads": 0,
    "streams": 0,
    "price": "249",
    "expireDate": "2021-02-16 13:59:11",
    "message": "Tak for køb af gavekortet (forudbestillingen). Bogen tilsendes ved udgivelsen.",
    "orderCreateDate": "2021-01-17 13:59:11",
    "mediaRelationUdis": ["umb://document/eb39a5eee85b4590b2049e4b1d7c609f"],
    "downloadUdis": [],
    "streamUdis": [],
    "mediaUdis": ["umb://document/eb39a5eee85b4590b2049e4b1d7c609f"],
    "downloadMediaCount": 0,
    "streamMediaCount": 0,
    "mediaCount": 1,
    "media": [
      {
        "udi": "umb://document/eb39a5eee85b4590b2049e4b1d7c609f",
        "key": "eb39a5ee-e85b-4590-b204-9e4b1d7c609f",
        "resolved": true,
        "id": 25348,
        "name": "Gavekort",
        "title": "Gavekort",
        "urls": ["/ilona-margibell/gavekort-til-bog/gavekort/"],
        "contentTypeAlias": "media",
        "videoID": "",
        "videoStatus": "",
        "videoThumbnailURL": "",
        "videoDownloadURL": "",
        "rawFile": "/media/2729/gavekort.pdf",
        "webContentURL": "",
        "thumbnail": "/media/2736/gavekort.jpg",
        "purchasePrice": "249",
        "rentalPrice": ""
      }
    ],
    "downloadMedia": [],
    "streamMedia": [],
    "mediaNames": ["Gavekort"],
    "mediaUrls": ["/ilona-margibell/gavekort-til-bog/gavekort/"],
    "videoDownloadURLs": [],
    "downloadMediaNames": [],
    "downloadMediaUrls": [],
    "downloadVideoDownloadURLs": [],
    "streamMediaNames": [],
    "streamMediaUrls": [],
    "streamVideoDownloadURLs": [],
    "properties": {
      "videoID": "",
      "email": "amrt@mail.dk",
      "streams": "",
      "downloads": "",
      "isPurchase": "1",
      "expireDate": "2021-02-16 13:59:11",
      "price": "249",
      "fullName": "Anne Mette Rønnow Torp",
      "message": "Tak for køb af gavekortet (forudbestillingen). Bogen tilsendes ved udgivelsen.",
      "media": "umb://document/eb39a5eee85b4590b2049e4b1d7c609f"
    }
  },
  {
    "id": 26593,
    "key": "d9d5befb-8d7a-462e-9765-b5c56b33daed",
    "udi": "umb://document/d9d5befb8d7a462e9765b5c56b33daed",
    "name": "c2uk31122020234936",
    "contentTypeAlias": "purchase",
    "published": true,
    "hasPublishedVersion": true,
    "createDate": "2020-12-31 23:49:47",
    "updateDate": "2020-12-31 23:49:47",
    "parentId": 25345,
    "path": "-1,1067,25340,25345,26593",
    "sortOrder": 10,
    "urls": ["/ilona-margibell/purchases/c2uk31122020234936/"],
    "fullName": "Bente Ravn",
    "email": "bente.ravn@hotmail.com",
    "isPurchase": true,
    "downloads": 0,
    "streams": 0,
    "price": "249",
    "expireDate": "2021-01-30 23:49:46",
    "message": "Tak for køb af gavekortet (forudbestillingen). Bogen tilsendes ved udgivelsen.",
    "orderCreateDate": "2020-12-31 23:49:47",
    "mediaRelationUdis": ["umb://document/eb39a5eee85b4590b2049e4b1d7c609f"],
    "downloadUdis": [],
    "streamUdis": [],
    "mediaUdis": ["umb://document/eb39a5eee85b4590b2049e4b1d7c609f"],
    "downloadMediaCount": 0,
    "streamMediaCount": 0,
    "mediaCount": 1,
    "media": [
      {
        "udi": "umb://document/eb39a5eee85b4590b2049e4b1d7c609f",
        "key": "eb39a5ee-e85b-4590-b204-9e4b1d7c609f",
        "resolved": true,
        "id": 25348,
        "name": "Gavekort",
        "title": "Gavekort",
        "urls": ["/ilona-margibell/gavekort-til-bog/gavekort/"],
        "contentTypeAlias": "media",
        "videoID": "",
        "videoStatus": "",
        "videoThumbnailURL": "",
        "videoDownloadURL": "",
        "rawFile": "/media/2729/gavekort.pdf",
        "webContentURL": "",
        "thumbnail": "/media/2736/gavekort.jpg",
        "purchasePrice": "249",
        "rentalPrice": ""
      }
    ],
    "downloadMedia": [],
    "streamMedia": [],
    "mediaNames": ["Gavekort"],
    "mediaUrls": ["/ilona-margibell/gavekort-til-bog/gavekort/"],
    "videoDownloadURLs": [],
    "downloadMediaNames": [],
    "downloadMediaUrls": [],
    "downloadVideoDownloadURLs": [],
    "streamMediaNames": [],
    "streamMediaUrls": [],
    "streamVideoDownloadURLs": [],
    "properties": {
      "videoID": "",
      "email": "bente.ravn@hotmail.com",
      "streams": "",
      "downloads": "",
      "isPurchase": "1",
      "expireDate": "2021-01-30 23:49:46",
      "price": "249",
      "fullName": "Bente Ravn",
      "message": "Tak for køb af gavekortet (forudbestillingen). Bogen tilsendes ved udgivelsen.",
      "media": "umb://document/eb39a5eee85b4590b2049e4b1d7c609f"
    }
  },
  {
    "id": 26591,
    "key": "ad4ff09f-e7f1-46fb-ab9c-30c9ce63534c",
    "udi": "umb://document/ad4ff09fe7f146fbab9c30c9ce63534c",
    "name": "6g7d31122020234816",
    "contentTypeAlias": "purchase",
    "published": true,
    "hasPublishedVersion": true,
    "createDate": "2020-12-31 23:48:34",
    "updateDate": "2020-12-31 23:48:34",
    "parentId": 25345,
    "path": "-1,1067,25340,25345,26591",
    "sortOrder": 9,
    "urls": ["/ilona-margibell/purchases/6g7d31122020234816/"],
    "fullName": "Bente Ravn",
    "email": "bente.ravn@hotmail.com",
    "isPurchase": true,
    "downloads": 0,
    "streams": 0,
    "price": "249",
    "expireDate": "2021-01-30 23:48:34",
    "message": "Tak for køb af gavekortet (forudbestillingen). Bogen tilsendes ved udgivelsen.",
    "orderCreateDate": "2020-12-31 23:48:34",
    "mediaRelationUdis": ["umb://document/eb39a5eee85b4590b2049e4b1d7c609f"],
    "downloadUdis": [],
    "streamUdis": [],
    "mediaUdis": ["umb://document/eb39a5eee85b4590b2049e4b1d7c609f"],
    "downloadMediaCount": 0,
    "streamMediaCount": 0,
    "mediaCount": 1,
    "media": [
      {
        "udi": "umb://document/eb39a5eee85b4590b2049e4b1d7c609f",
        "key": "eb39a5ee-e85b-4590-b204-9e4b1d7c609f",
        "resolved": true,
        "id": 25348,
        "name": "Gavekort",
        "title": "Gavekort",
        "urls": ["/ilona-margibell/gavekort-til-bog/gavekort/"],
        "contentTypeAlias": "media",
        "videoID": "",
        "videoStatus": "",
        "videoThumbnailURL": "",
        "videoDownloadURL": "",
        "rawFile": "/media/2729/gavekort.pdf",
        "webContentURL": "",
        "thumbnail": "/media/2736/gavekort.jpg",
        "purchasePrice": "249",
        "rentalPrice": ""
      }
    ],
    "downloadMedia": [],
    "streamMedia": [],
    "mediaNames": ["Gavekort"],
    "mediaUrls": ["/ilona-margibell/gavekort-til-bog/gavekort/"],
    "videoDownloadURLs": [],
    "downloadMediaNames": [],
    "downloadMediaUrls": [],
    "downloadVideoDownloadURLs": [],
    "streamMediaNames": [],
    "streamMediaUrls": [],
    "streamVideoDownloadURLs": [],
    "properties": {
      "videoID": "",
      "email": "bente.ravn@hotmail.com",
      "streams": "",
      "downloads": "",
      "isPurchase": "1",
      "expireDate": "2021-01-30 23:48:34",
      "price": "249",
      "fullName": "Bente Ravn",
      "message": "Tak for køb af gavekortet (forudbestillingen). Bogen tilsendes ved udgivelsen.",
      "media": "umb://document/eb39a5eee85b4590b2049e4b1d7c609f"
    }
  },
  {
    "id": 26438,
    "key": "ff8ee277-829d-426e-afaa-6547edab9844",
    "udi": "umb://document/ff8ee277829d426eafaa6547edab9844",
    "name": "q71930122020144604",
    "contentTypeAlias": "purchase",
    "published": true,
    "hasPublishedVersion": true,
    "createDate": "2020-12-30 14:48:29",
    "updateDate": "2020-12-30 14:48:29",
    "parentId": 25345,
    "path": "-1,1067,25340,25345,26438",
    "sortOrder": 8,
    "urls": ["/ilona-margibell/purchases/q71930122020144604/"],
    "fullName": "Lina Bjørnø",
    "email": "linabjorno@gmail.com",
    "isPurchase": true,
    "downloads": 0,
    "streams": 0,
    "price": "249",
    "expireDate": "2021-01-29 14:48:28",
    "message": "Tak for køb af gavekortet (forudbestillingen). Bogen tilsendes ved udgivelsen.",
    "orderCreateDate": "2020-12-30 14:48:29",
    "mediaRelationUdis": ["umb://document/eb39a5eee85b4590b2049e4b1d7c609f"],
    "downloadUdis": [],
    "streamUdis": [],
    "mediaUdis": ["umb://document/eb39a5eee85b4590b2049e4b1d7c609f"],
    "downloadMediaCount": 0,
    "streamMediaCount": 0,
    "mediaCount": 1,
    "media": [
      {
        "udi": "umb://document/eb39a5eee85b4590b2049e4b1d7c609f",
        "key": "eb39a5ee-e85b-4590-b204-9e4b1d7c609f",
        "resolved": true,
        "id": 25348,
        "name": "Gavekort",
        "title": "Gavekort",
        "urls": ["/ilona-margibell/gavekort-til-bog/gavekort/"],
        "contentTypeAlias": "media",
        "videoID": "",
        "videoStatus": "",
        "videoThumbnailURL": "",
        "videoDownloadURL": "",
        "rawFile": "/media/2729/gavekort.pdf",
        "webContentURL": "",
        "thumbnail": "/media/2736/gavekort.jpg",
        "purchasePrice": "249",
        "rentalPrice": ""
      }
    ],
    "downloadMedia": [],
    "streamMedia": [],
    "mediaNames": ["Gavekort"],
    "mediaUrls": ["/ilona-margibell/gavekort-til-bog/gavekort/"],
    "videoDownloadURLs": [],
    "downloadMediaNames": [],
    "downloadMediaUrls": [],
    "downloadVideoDownloadURLs": [],
    "streamMediaNames": [],
    "streamMediaUrls": [],
    "streamVideoDownloadURLs": [],
    "properties": {
      "videoID": "",
      "email": "linabjorno@gmail.com",
      "streams": "",
      "downloads": "",
      "isPurchase": "1",
      "expireDate": "2021-01-29 14:48:28",
      "price": "249",
      "fullName": "Lina Bjørnø",
      "message": "Tak for køb af gavekortet (forudbestillingen). Bogen tilsendes ved udgivelsen.",
      "media": "umb://document/eb39a5eee85b4590b2049e4b1d7c609f"
    }
  },
  {
    "id": 26433,
    "key": "b02bede2-66d3-45b6-aa3a-f48c141bf320",
    "udi": "umb://document/b02bede266d345b6aa3af48c141bf320",
    "name": "etq330122020144138",
    "contentTypeAlias": "purchase",
    "published": true,
    "hasPublishedVersion": true,
    "createDate": "2020-12-30 14:43:37",
    "updateDate": "2020-12-30 14:43:37",
    "parentId": 25345,
    "path": "-1,1067,25340,25345,26433",
    "sortOrder": 7,
    "urls": ["/ilona-margibell/purchases/etq330122020144138/"],
    "fullName": "Lina Bjørnø",
    "email": "linabjorno@gmail.vom",
    "isPurchase": true,
    "downloads": 0,
    "streams": 0,
    "price": "249",
    "expireDate": "2021-01-29 14:43:37",
    "message": "Tak for køb af gavekortet (forudbestillingen). Bogen tilsendes ved udgivelsen.",
    "orderCreateDate": "2020-12-30 14:43:37",
    "mediaRelationUdis": ["umb://document/eb39a5eee85b4590b2049e4b1d7c609f"],
    "downloadUdis": [],
    "streamUdis": [],
    "mediaUdis": ["umb://document/eb39a5eee85b4590b2049e4b1d7c609f"],
    "downloadMediaCount": 0,
    "streamMediaCount": 0,
    "mediaCount": 1,
    "media": [
      {
        "udi": "umb://document/eb39a5eee85b4590b2049e4b1d7c609f",
        "key": "eb39a5ee-e85b-4590-b204-9e4b1d7c609f",
        "resolved": true,
        "id": 25348,
        "name": "Gavekort",
        "title": "Gavekort",
        "urls": ["/ilona-margibell/gavekort-til-bog/gavekort/"],
        "contentTypeAlias": "media",
        "videoID": "",
        "videoStatus": "",
        "videoThumbnailURL": "",
        "videoDownloadURL": "",
        "rawFile": "/media/2729/gavekort.pdf",
        "webContentURL": "",
        "thumbnail": "/media/2736/gavekort.jpg",
        "purchasePrice": "249",
        "rentalPrice": ""
      }
    ],
    "downloadMedia": [],
    "streamMedia": [],
    "mediaNames": ["Gavekort"],
    "mediaUrls": ["/ilona-margibell/gavekort-til-bog/gavekort/"],
    "videoDownloadURLs": [],
    "downloadMediaNames": [],
    "downloadMediaUrls": [],
    "downloadVideoDownloadURLs": [],
    "streamMediaNames": [],
    "streamMediaUrls": [],
    "streamVideoDownloadURLs": [],
    "properties": {
      "videoID": "",
      "email": "linabjorno@gmail.vom",
      "streams": "",
      "downloads": "",
      "isPurchase": "1",
      "expireDate": "2021-01-29 14:43:37",
      "price": "249",
      "fullName": "Lina Bjørnø",
      "message": "Tak for køb af gavekortet (forudbestillingen). Bogen tilsendes ved udgivelsen.",
      "media": "umb://document/eb39a5eee85b4590b2049e4b1d7c609f"
    }
  },
  {
    "id": 25948,
    "key": "7e456a19-11ca-4a1c-aaf4-0f05a0b639e2",
    "udi": "umb://document/7e456a1911ca4a1caaf40f05a0b639e2",
    "name": "816s27122020174924",
    "contentTypeAlias": "purchase",
    "published": true,
    "hasPublishedVersion": true,
    "createDate": "2020-12-27 17:50:11",
    "updateDate": "2020-12-27 17:50:11",
    "parentId": 25345,
    "path": "-1,1067,25340,25345,25948",
    "sortOrder": 6,
    "urls": ["/ilona-margibell/purchases/816s27122020174924/"],
    "fullName": "Louise Hardisty Olesen",
    "email": "louisehardisty@gmail.com",
    "isPurchase": true,
    "downloads": 0,
    "streams": 0,
    "price": "249",
    "expireDate": "2021-01-26 17:50:11",
    "message": "Tak for køb af gavekortet (forudbestillingen). Bogen tilsendes ved udgivelsen.",
    "orderCreateDate": "2020-12-27 17:50:11",
    "mediaRelationUdis": ["umb://document/eb39a5eee85b4590b2049e4b1d7c609f"],
    "downloadUdis": [],
    "streamUdis": [],
    "mediaUdis": ["umb://document/eb39a5eee85b4590b2049e4b1d7c609f"],
    "downloadMediaCount": 0,
    "streamMediaCount": 0,
    "mediaCount": 1,
    "media": [
      {
        "udi": "umb://document/eb39a5eee85b4590b2049e4b1d7c609f",
        "key": "eb39a5ee-e85b-4590-b204-9e4b1d7c609f",
        "resolved": true,
        "id": 25348,
        "name": "Gavekort",
        "title": "Gavekort",
        "urls": ["/ilona-margibell/gavekort-til-bog/gavekort/"],
        "contentTypeAlias": "media",
        "videoID": "",
        "videoStatus": "",
        "videoThumbnailURL": "",
        "videoDownloadURL": "",
        "rawFile": "/media/2729/gavekort.pdf",
        "webContentURL": "",
        "thumbnail": "/media/2736/gavekort.jpg",
        "purchasePrice": "249",
        "rentalPrice": ""
      }
    ],
    "downloadMedia": [],
    "streamMedia": [],
    "mediaNames": ["Gavekort"],
    "mediaUrls": ["/ilona-margibell/gavekort-til-bog/gavekort/"],
    "videoDownloadURLs": [],
    "downloadMediaNames": [],
    "downloadMediaUrls": [],
    "downloadVideoDownloadURLs": [],
    "streamMediaNames": [],
    "streamMediaUrls": [],
    "streamVideoDownloadURLs": [],
    "properties": {
      "videoID": "",
      "email": "louisehardisty@gmail.com",
      "streams": "",
      "downloads": "",
      "isPurchase": "1",
      "expireDate": "2021-01-26 17:50:11",
      "price": "249",
      "fullName": "Louise Hardisty Olesen",
      "message": "Tak for køb af gavekortet (forudbestillingen). Bogen tilsendes ved udgivelsen.",
      "media": "umb://document/eb39a5eee85b4590b2049e4b1d7c609f"
    }
  },
  {
    "id": 25945,
    "key": "4e94478f-e8f2-4672-b5a9-612878729ed2",
    "udi": "umb://document/4e94478fe8f24672b5a9612878729ed2",
    "name": "39b327122020174650",
    "contentTypeAlias": "purchase",
    "published": true,
    "hasPublishedVersion": true,
    "createDate": "2020-12-27 17:48:04",
    "updateDate": "2020-12-27 17:48:04",
    "parentId": 25345,
    "path": "-1,1067,25340,25345,25945",
    "sortOrder": 5,
    "urls": ["/ilona-margibell/purchases/39b327122020174650/"],
    "fullName": "Louise Hardisty Olesen",
    "email": "louisehardisty@gmail.com",
    "isPurchase": true,
    "downloads": 0,
    "streams": 0,
    "price": "249",
    "expireDate": "2021-01-26 17:48:04",
    "message": "Tak for køb af gavekortet (forudbestillingen). Bogen tilsendes ved udgivelsen.",
    "orderCreateDate": "2020-12-27 17:48:04",
    "mediaRelationUdis": ["umb://document/eb39a5eee85b4590b2049e4b1d7c609f"],
    "downloadUdis": [],
    "streamUdis": [],
    "mediaUdis": ["umb://document/eb39a5eee85b4590b2049e4b1d7c609f"],
    "downloadMediaCount": 0,
    "streamMediaCount": 0,
    "mediaCount": 1,
    "media": [
      {
        "udi": "umb://document/eb39a5eee85b4590b2049e4b1d7c609f",
        "key": "eb39a5ee-e85b-4590-b204-9e4b1d7c609f",
        "resolved": true,
        "id": 25348,
        "name": "Gavekort",
        "title": "Gavekort",
        "urls": ["/ilona-margibell/gavekort-til-bog/gavekort/"],
        "contentTypeAlias": "media",
        "videoID": "",
        "videoStatus": "",
        "videoThumbnailURL": "",
        "videoDownloadURL": "",
        "rawFile": "/media/2729/gavekort.pdf",
        "webContentURL": "",
        "thumbnail": "/media/2736/gavekort.jpg",
        "purchasePrice": "249",
        "rentalPrice": ""
      }
    ],
    "downloadMedia": [],
    "streamMedia": [],
    "mediaNames": ["Gavekort"],
    "mediaUrls": ["/ilona-margibell/gavekort-til-bog/gavekort/"],
    "videoDownloadURLs": [],
    "downloadMediaNames": [],
    "downloadMediaUrls": [],
    "downloadVideoDownloadURLs": [],
    "streamMediaNames": [],
    "streamMediaUrls": [],
    "streamVideoDownloadURLs": [],
    "properties": {
      "videoID": "",
      "email": "louisehardisty@gmail.com",
      "streams": "",
      "downloads": "",
      "isPurchase": "1",
      "expireDate": "2021-01-26 17:48:04",
      "price": "249",
      "fullName": "Louise Hardisty Olesen",
      "message": "Tak for køb af gavekortet (forudbestillingen). Bogen tilsendes ved udgivelsen.",
      "media": "umb://document/eb39a5eee85b4590b2049e4b1d7c609f"
    }
  },
  {
    "id": 25896,
    "key": "cac986d8-38e1-4b11-b520-f234d09d9091",
    "udi": "umb://document/cac986d838e14b11b520f234d09d9091",
    "name": "rvz827122020131608",
    "contentTypeAlias": "purchase",
    "published": true,
    "hasPublishedVersion": true,
    "createDate": "2020-12-27 13:17:03",
    "updateDate": "2020-12-27 13:17:03",
    "parentId": 25345,
    "path": "-1,1067,25340,25345,25896",
    "sortOrder": 4,
    "urls": ["/ilona-margibell/purchases/rvz827122020131608/"],
    "fullName": "Peter Båtz",
    "email": "peter.baatz@mail.dk",
    "isPurchase": true,
    "downloads": 0,
    "streams": 0,
    "price": "249",
    "expireDate": "2021-01-26 13:17:03",
    "message": "Tak for køb af gavekortet (forudbestillingen). Bogen tilsendes ved udgivelsen.",
    "orderCreateDate": "2020-12-27 13:17:03",
    "mediaRelationUdis": ["umb://document/eb39a5eee85b4590b2049e4b1d7c609f"],
    "downloadUdis": [],
    "streamUdis": [],
    "mediaUdis": ["umb://document/eb39a5eee85b4590b2049e4b1d7c609f"],
    "downloadMediaCount": 0,
    "streamMediaCount": 0,
    "mediaCount": 1,
    "media": [
      {
        "udi": "umb://document/eb39a5eee85b4590b2049e4b1d7c609f",
        "key": "eb39a5ee-e85b-4590-b204-9e4b1d7c609f",
        "resolved": true,
        "id": 25348,
        "name": "Gavekort",
        "title": "Gavekort",
        "urls": ["/ilona-margibell/gavekort-til-bog/gavekort/"],
        "contentTypeAlias": "media",
        "videoID": "",
        "videoStatus": "",
        "videoThumbnailURL": "",
        "videoDownloadURL": "",
        "rawFile": "/media/2729/gavekort.pdf",
        "webContentURL": "",
        "thumbnail": "/media/2736/gavekort.jpg",
        "purchasePrice": "249",
        "rentalPrice": ""
      }
    ],
    "downloadMedia": [],
    "streamMedia": [],
    "mediaNames": ["Gavekort"],
    "mediaUrls": ["/ilona-margibell/gavekort-til-bog/gavekort/"],
    "videoDownloadURLs": [],
    "downloadMediaNames": [],
    "downloadMediaUrls": [],
    "downloadVideoDownloadURLs": [],
    "streamMediaNames": [],
    "streamMediaUrls": [],
    "streamVideoDownloadURLs": [],
    "properties": {
      "videoID": "",
      "email": "peter.baatz@mail.dk",
      "streams": "",
      "downloads": "",
      "isPurchase": "1",
      "expireDate": "2021-01-26 13:17:03",
      "price": "249",
      "fullName": "Peter Båtz",
      "message": "Tak for køb af gavekortet (forudbestillingen). Bogen tilsendes ved udgivelsen.",
      "media": "umb://document/eb39a5eee85b4590b2049e4b1d7c609f"
    }
  },
  {
    "id": 25750,
    "key": "1531feae-22dd-427e-9f35-930dd0a47876",
    "udi": "umb://document/1531feae22dd427e9f35930dd0a47876",
    "name": "8v3126122020155012",
    "contentTypeAlias": "purchase",
    "published": true,
    "hasPublishedVersion": true,
    "createDate": "2020-12-26 15:50:34",
    "updateDate": "2020-12-26 15:50:34",
    "parentId": 25345,
    "path": "-1,1067,25340,25345,25750",
    "sortOrder": 3,
    "urls": ["/ilona-margibell/purchases/8v3126122020155012/"],
    "fullName": "Mei Song Bechsgaard",
    "email": "meisong2512@hotmail.com",
    "isPurchase": true,
    "downloads": 0,
    "streams": 0,
    "price": "249",
    "expireDate": "2021-01-25 15:50:33",
    "message": "Tak for køb af gavekortet (forudbestillingen). Bogen tilsendes ved udgivelsen.",
    "orderCreateDate": "2020-12-26 15:50:34",
    "mediaRelationUdis": ["umb://document/eb39a5eee85b4590b2049e4b1d7c609f"],
    "downloadUdis": [],
    "streamUdis": [],
    "mediaUdis": ["umb://document/eb39a5eee85b4590b2049e4b1d7c609f"],
    "downloadMediaCount": 0,
    "streamMediaCount": 0,
    "mediaCount": 1,
    "media": [
      {
        "udi": "umb://document/eb39a5eee85b4590b2049e4b1d7c609f",
        "key": "eb39a5ee-e85b-4590-b204-9e4b1d7c609f",
        "resolved": true,
        "id": 25348,
        "name": "Gavekort",
        "title": "Gavekort",
        "urls": ["/ilona-margibell/gavekort-til-bog/gavekort/"],
        "contentTypeAlias": "media",
        "videoID": "",
        "videoStatus": "",
        "videoThumbnailURL": "",
        "videoDownloadURL": "",
        "rawFile": "/media/2729/gavekort.pdf",
        "webContentURL": "",
        "thumbnail": "/media/2736/gavekort.jpg",
        "purchasePrice": "249",
        "rentalPrice": ""
      }
    ],
    "downloadMedia": [],
    "streamMedia": [],
    "mediaNames": ["Gavekort"],
    "mediaUrls": ["/ilona-margibell/gavekort-til-bog/gavekort/"],
    "videoDownloadURLs": [],
    "downloadMediaNames": [],
    "downloadMediaUrls": [],
    "downloadVideoDownloadURLs": [],
    "streamMediaNames": [],
    "streamMediaUrls": [],
    "streamVideoDownloadURLs": [],
    "properties": {
      "videoID": "",
      "email": "meisong2512@hotmail.com",
      "streams": "",
      "downloads": "",
      "isPurchase": "1",
      "expireDate": "2021-01-25 15:50:33",
      "price": "249",
      "fullName": "Mei Song Bechsgaard",
      "message": "Tak for køb af gavekortet (forudbestillingen). Bogen tilsendes ved udgivelsen.",
      "media": "umb://document/eb39a5eee85b4590b2049e4b1d7c609f"
    }
  },
  {
    "id": 25747,
    "key": "747a6d75-2578-4a96-865a-9ce3af71eb23",
    "udi": "umb://document/747a6d7525784a96865a9ce3af71eb23",
    "name": "428526122020154804",
    "contentTypeAlias": "purchase",
    "published": true,
    "hasPublishedVersion": true,
    "createDate": "2020-12-26 15:48:32",
    "updateDate": "2020-12-26 15:48:32",
    "parentId": 25345,
    "path": "-1,1067,25340,25345,25747",
    "sortOrder": 2,
    "urls": ["/ilona-margibell/purchases/428526122020154804/"],
    "fullName": "Mei Song Bechsgaard",
    "email": "meisong2512@hotmail.com",
    "isPurchase": true,
    "downloads": 0,
    "streams": 0,
    "price": "249",
    "expireDate": "2021-01-25 15:48:32",
    "message": "Tak for køb af gavekortet (forudbestillingen). Bogen tilsendes ved udgivelsen.",
    "orderCreateDate": "2020-12-26 15:48:32",
    "mediaRelationUdis": ["umb://document/eb39a5eee85b4590b2049e4b1d7c609f"],
    "downloadUdis": [],
    "streamUdis": [],
    "mediaUdis": ["umb://document/eb39a5eee85b4590b2049e4b1d7c609f"],
    "downloadMediaCount": 0,
    "streamMediaCount": 0,
    "mediaCount": 1,
    "media": [
      {
        "udi": "umb://document/eb39a5eee85b4590b2049e4b1d7c609f",
        "key": "eb39a5ee-e85b-4590-b204-9e4b1d7c609f",
        "resolved": true,
        "id": 25348,
        "name": "Gavekort",
        "title": "Gavekort",
        "urls": ["/ilona-margibell/gavekort-til-bog/gavekort/"],
        "contentTypeAlias": "media",
        "videoID": "",
        "videoStatus": "",
        "videoThumbnailURL": "",
        "videoDownloadURL": "",
        "rawFile": "/media/2729/gavekort.pdf",
        "webContentURL": "",
        "thumbnail": "/media/2736/gavekort.jpg",
        "purchasePrice": "249",
        "rentalPrice": ""
      }
    ],
    "downloadMedia": [],
    "streamMedia": [],
    "mediaNames": ["Gavekort"],
    "mediaUrls": ["/ilona-margibell/gavekort-til-bog/gavekort/"],
    "videoDownloadURLs": [],
    "downloadMediaNames": [],
    "downloadMediaUrls": [],
    "downloadVideoDownloadURLs": [],
    "streamMediaNames": [],
    "streamMediaUrls": [],
    "streamVideoDownloadURLs": [],
    "properties": {
      "videoID": "",
      "email": "meisong2512@hotmail.com",
      "streams": "",
      "downloads": "",
      "isPurchase": "1",
      "expireDate": "2021-01-25 15:48:32",
      "price": "249",
      "fullName": "Mei Song Bechsgaard",
      "message": "Tak for køb af gavekortet (forudbestillingen). Bogen tilsendes ved udgivelsen.",
      "media": "umb://document/eb39a5eee85b4590b2049e4b1d7c609f"
    }
  },
  {
    "id": 25739,
    "key": "046bd1af-9bb8-492d-a376-2cd73d60eb32",
    "udi": "umb://document/046bd1af9bb8492da3762cd73d60eb32",
    "name": "2m9s26122020143331",
    "contentTypeAlias": "purchase",
    "published": true,
    "hasPublishedVersion": true,
    "createDate": "2020-12-26 14:34:27",
    "updateDate": "2020-12-26 14:34:27",
    "parentId": 25345,
    "path": "-1,1067,25340,25345,25739",
    "sortOrder": 1,
    "urls": ["/ilona-margibell/purchases/2m9s26122020143331/"],
    "fullName": "Peter Båtz",
    "email": "peter.baatz@mail.dk",
    "isPurchase": true,
    "downloads": 0,
    "streams": 0,
    "price": "249",
    "expireDate": "2021-01-25 14:34:27",
    "message": "Tak for køb af gavekortet (forudbestillingen). Bogen tilsendes ved udgivelsen.",
    "orderCreateDate": "2020-12-26 14:34:27",
    "mediaRelationUdis": ["umb://document/eb39a5eee85b4590b2049e4b1d7c609f"],
    "downloadUdis": [],
    "streamUdis": [],
    "mediaUdis": ["umb://document/eb39a5eee85b4590b2049e4b1d7c609f"],
    "downloadMediaCount": 0,
    "streamMediaCount": 0,
    "mediaCount": 1,
    "media": [
      {
        "udi": "umb://document/eb39a5eee85b4590b2049e4b1d7c609f",
        "key": "eb39a5ee-e85b-4590-b204-9e4b1d7c609f",
        "resolved": true,
        "id": 25348,
        "name": "Gavekort",
        "title": "Gavekort",
        "urls": ["/ilona-margibell/gavekort-til-bog/gavekort/"],
        "contentTypeAlias": "media",
        "videoID": "",
        "videoStatus": "",
        "videoThumbnailURL": "",
        "videoDownloadURL": "",
        "rawFile": "/media/2729/gavekort.pdf",
        "webContentURL": "",
        "thumbnail": "/media/2736/gavekort.jpg",
        "purchasePrice": "249",
        "rentalPrice": ""
      }
    ],
    "downloadMedia": [],
    "streamMedia": [],
    "mediaNames": ["Gavekort"],
    "mediaUrls": ["/ilona-margibell/gavekort-til-bog/gavekort/"],
    "videoDownloadURLs": [],
    "downloadMediaNames": [],
    "downloadMediaUrls": [],
    "downloadVideoDownloadURLs": [],
    "streamMediaNames": [],
    "streamMediaUrls": [],
    "streamVideoDownloadURLs": [],
    "properties": {
      "videoID": "",
      "email": "peter.baatz@mail.dk",
      "streams": "",
      "downloads": "",
      "isPurchase": "1",
      "expireDate": "2021-01-25 14:34:27",
      "price": "249",
      "fullName": "Peter Båtz",
      "message": "Tak for køb af gavekortet (forudbestillingen). Bogen tilsendes ved udgivelsen.",
      "media": "umb://document/eb39a5eee85b4590b2049e4b1d7c609f"
    }
  },
  {
    "id": 25530,
    "key": "e2969100-3165-4c15-8a3d-aa050e570bf0",
    "udi": "umb://document/e296910031654c158a3daa050e570bf0",
    "name": "99vj24122020001703",
    "contentTypeAlias": "purchase",
    "published": true,
    "hasPublishedVersion": true,
    "createDate": "2020-12-24 00:18:11",
    "updateDate": "2020-12-24 00:18:11",
    "parentId": 25345,
    "path": "-1,1067,25340,25345,25530",
    "sortOrder": 0,
    "urls": ["/ilona-margibell/purchases/99vj24122020001703/"],
    "fullName": "Ilona Margibell Bechsgaard",
    "email": "ilonamargibell@gmail.com",
    "isPurchase": true,
    "downloads": 0,
    "streams": 0,
    "price": "249",
    "expireDate": "2021-01-23 00:18:10",
    "message": "Tak for køb af gavekortet (forudbestillingen). Bogen tilsendes ved udgivelsen.",
    "orderCreateDate": "2020-12-24 00:18:11",
    "mediaRelationUdis": ["umb://document/eb39a5eee85b4590b2049e4b1d7c609f"],
    "downloadUdis": [],
    "streamUdis": [],
    "mediaUdis": ["umb://document/eb39a5eee85b4590b2049e4b1d7c609f"],
    "downloadMediaCount": 0,
    "streamMediaCount": 0,
    "mediaCount": 1,
    "media": [
      {
        "udi": "umb://document/eb39a5eee85b4590b2049e4b1d7c609f",
        "key": "eb39a5ee-e85b-4590-b204-9e4b1d7c609f",
        "resolved": true,
        "id": 25348,
        "name": "Gavekort",
        "title": "Gavekort",
        "urls": ["/ilona-margibell/gavekort-til-bog/gavekort/"],
        "contentTypeAlias": "media",
        "videoID": "",
        "videoStatus": "",
        "videoThumbnailURL": "",
        "videoDownloadURL": "",
        "rawFile": "/media/2729/gavekort.pdf",
        "webContentURL": "",
        "thumbnail": "/media/2736/gavekort.jpg",
        "purchasePrice": "249",
        "rentalPrice": ""
      }
    ],
    "downloadMedia": [],
    "streamMedia": [],
    "mediaNames": ["Gavekort"],
    "mediaUrls": ["/ilona-margibell/gavekort-til-bog/gavekort/"],
    "videoDownloadURLs": [],
    "downloadMediaNames": [],
    "downloadMediaUrls": [],
    "downloadVideoDownloadURLs": [],
    "streamMediaNames": [],
    "streamMediaUrls": [],
    "streamVideoDownloadURLs": [],
    "properties": {
      "videoID": "",
      "email": "ilonamargibell@gmail.com",
      "streams": "",
      "downloads": "",
      "isPurchase": "1",
      "expireDate": "2021-01-23 00:18:10",
      "price": "249",
      "fullName": "Ilona Margibell Bechsgaard",
      "message": "Tak for køb af gavekortet (forudbestillingen). Bogen tilsendes ved udgivelsen.",
      "media": "umb://document/eb39a5eee85b4590b2049e4b1d7c609f"
    }
  }
]
